cfv/__init__.py
cfv/caching.py
cfv/cftypes.py
cfv/common.py
cfv/fileutil.py
cfv/hash.py
cfv/osutil.py
cfv/progress.py
cfv/strutil.py
cfv/term.py
cfv/ui.py
cfv/BitTorrent/LICENSE.txt
cfv/BitTorrent/__init__.py
cfv/BitTorrent/bencode.py
cfv/BitTorrent/btformats.py
cfv-3.1.0.data/data/share/man/man1/cfv.1
cfv-3.1.0.dist-info/COPYING
cfv-3.1.0.dist-info/METADATA
cfv-3.1.0.dist-info/WHEEL
cfv-3.1.0.dist-info/entry_points.txt
cfv-3.1.0.dist-info/top_level.txt
cfv-3.1.0.dist-info/RECORD
