Metadata-Version: 2.1
Name: cfv
Version: 3.1.0
Summary: Command-line File Verify - versatile file checksum creator and verifier
Home-page: https://github.com/cfv-project/cfv
Author: David Lisa Gnedt (Current Maintainer)
Author-email: cfv-project@davizone.at
License: GPL
Project-URL: Bug Tracker, https://github.com/cfv-project/cfv/issues
Project-URL: Source Code, https://github.com/cfv-project/cfv
Project-URL: Original Project, http://cfv.sourceforge.net/
Keywords: cfv checksum verify sfv csv crc bsdmd5 md5sum sha1sum sha224sum sha256sum sha384sum sha512sum torrent par par2
Classifier: Development Status :: 5 - Production/Stable
Classifier: Environment :: Console
Classifier: Topic :: System :: Archiving
Classifier: Topic :: Utilities
Classifier: License :: OSI Approved :: GNU General Public License v2 or later (GPLv2+)
Classifier: Programming Language :: Python :: 3
Classifier: Programming Language :: Python :: 3.6
Classifier: Programming Language :: Python :: 3.7
Classifier: Programming Language :: Python :: 3.8
Classifier: Programming Language :: Python :: 3.9
Classifier: Programming Language :: Python :: 3.10
Classifier: Programming Language :: Python :: 3.11
Classifier: Programming Language :: Python :: 3.12
Classifier: Programming Language :: Python :: 3.13
Requires-Python: >=3.6
License-File: COPYING
